scurry_kit/__init__.py
scurry_kit/addons/__init__.py
scurry_kit/addons/commands.py
scurry_kit/addons/components.py
scurry_kit/addons/events.py
scurry_kit/addons/hooks.py
scurry_kit/addons/logging.py
scurry_kit/addons/prefix.py
scurry_kit/addons/builders/__init__.py
scurry_kit/addons/builders/action_rows.py
scurry_kit/addons/builders/container.py
scurry_kit/addons/builders/embeds.py
scurry_kit/addons/builders/modals.py
scurry_kit/addons/cache/__init__.py
scurry_kit/addons/cache/bot_emojis.py
scurry_kit/addons/cache/channel.py
scurry_kit/addons/cache/guild_emojis.py
scurry_kit/addons/cache/role.py
scurry_kit-0.10.3.dist-info/licenses/LICENSE
scurry_kit-0.10.3.dist-info/METADATA
scurry_kit-0.10.3.dist-info/WHEEL
scurry_kit-0.10.3.dist-info/top_level.txt
scurry_kit-0.10.3.dist-info/RECORD
