Metadata-Version: 2.4
Name: scurry-kit
Version: 0.10.3
Summary: A lightweight routing and command kit built on top of ScurryPy.
Author: Furmissile
Requires-Python: >=3.10
License-File: LICENSE
Requires-Dist: scurrypy>=0.18.0
Dynamic: license-file
